djangocms_zb_polls/__init__.py
djangocms_zb_polls/admin.py
djangocms_zb_polls/apps.py
djangocms_zb_polls/cms_plugins.py
djangocms_zb_polls/models.py
djangocms_zb_polls/tests.py
djangocms_zb_polls/views.py
djangocms_zb_polls/admin_views/__init__.py
djangocms_zb_polls/admin_views/answer.py
djangocms_zb_polls/admin_views/poll.py
djangocms_zb_polls/admin_views/question.py
djangocms_zb_polls/forms/__init__.py
djangocms_zb_polls/forms/multi_email_field.py
djangocms_zb_polls/forms/poll.py
djangocms_zb_polls/forms/send_answers.py
djangocms_zb_polls/lib/__init__.py
djangocms_zb_polls/lib/enums.py
djangocms_zb_polls/lib/fields.py
djangocms_zb_polls/lib/get_file_excel_answers.py
djangocms_zb_polls/lib/widgets.py
djangocms_zb_polls/locale/es/LC_MESSAGES/django.mo
djangocms_zb_polls/locale/es/LC_MESSAGES/django.po
djangocms_zb_polls/migrations/0001_initial.py
djangocms_zb_polls/migrations/__init__.py
djangocms_zb_polls/static/djangocms_zb_polls/css/base.css
djangocms_zb_polls/static/djangocms_zb_polls/js/rating.js
djangocms_zb_polls/templates/djangocms_zb_polls/base.html
djangocms_zb_polls/templates/djangocms_zb_polls/send_answers.html
djangocms_zb_polls/templates/djangocms_zb_polls/mail/poll_report_responses.txt
djangocms_zb_polls/templates/djangocms_zb_polls/mail/poll_responses.txt
djangocms_zb_polls/templates/djangocms_zb_polls/plugins/bootstrap5/style_one/plugin.html
djangocms_zb_polls/templates/djangocms_zb_polls/plugins/default/plugin.html
djangocms_zb_polls/templates/djangocms_zb_polls/widgets/star_rating.html
djangocms_zb_polls/templates/djangocms_zb_polls/widgets/zb_select_option.html
djangocms_zb_polls/templatetags/__init__.py
djangocms_zb_polls/templatetags/polls_tags.py
djangocms_zb_polls-1.0.2.dist-info/licenses/LICENSE
djangocms_zb_polls-1.0.2.dist-info/METADATA
djangocms_zb_polls-1.0.2.dist-info/WHEEL
djangocms_zb_polls-1.0.2.dist-info/top_level.txt
djangocms_zb_polls-1.0.2.dist-info/RECORD
