Metadata-Version: 2.4
Name: djangocms-zb-polls
Version: 1.0.2
Summary: Zibanu Polls Plugin for Django CMS
Author-email: Jhony Gonzalez <jhonny.gonzalez@cqinversiones.co>
License-Expression: GPL-3.0-or-later
Keywords: django,zibanu,polls
Classifier: Programming Language :: Python :: 3.9
Classifier: Programming Language :: Python :: 3.10
Classifier: Programming Language :: Python :: 3.11
Classifier: Development Status :: 5 - Production/Stable
Classifier: Framework :: Django
Classifier: Framework :: Django :: 3.2
Classifier: Framework :: Django :: 4
Classifier: Framework :: Django :: 5
Classifier: Environment :: Web Environment
Classifier: Operating System :: OS Independent
Classifier: Topic :: Internet :: WWW/HTTP
Requires-Python: >=3.7
License-File: LICENSE
Requires-Dist: Django>=3.2
Requires-Dist: django-cms>=3.9
Requires-Dist: pandas
Requires-Dist: openpyxl
Dynamic: license-file
